AUTHORS
COPYING
README.md
pyproject.toml
setup.cfg
setup.py
data/ws/README
laniakea_spark.egg-info/PKG-INFO
laniakea_spark.egg-info/SOURCES.txt
laniakea_spark.egg-info/dependency_links.txt
laniakea_spark.egg-info/entry_points.txt
laniakea_spark.egg-info/not-zip-safe
laniakea_spark.egg-info/requires.txt
laniakea_spark.egg-info/top_level.txt
spark/__init__.py
spark/cli.py
spark/config.py
spark/connection.py
spark/daemon.py
spark/joblog.py
spark/worker.py
spark/runners/__init__.py
spark/runners/debspawn.py
spark/runners/image_build.py
spark/utils/__init__.py
spark/utils/command.py
spark/utils/deb822.py
spark/utils/firehose.py
spark/utils/misc.py
spark/utils/workspace.py