Metadata-Version: 2.1
Name: laniakea-spark
Version: 0.1.1
Summary: Generic distributed job runner for Laniakea.
Home-page: https://laniakea-hq.rtfd.io
Author: Matthias Klumpp
Author-email: Matthias Klumpp <matthias@tenstral.net>
License: LGPL-3.0-or-later
Project-URL: Documentation, https://github.com/lkhq/laniakea-spark
Project-URL: Source, https://github.com/lkhq/laniakea-spark
Platform: any
Requires-Python: >=3.9
License-File: COPYING
License-File: AUTHORS
